consul2nginx
