Metadata-Version: 1.0
Name: consul2nginx
Version: 0.0.17
Summary: Create nginx configuration from consul
Home-page: https://github.com/afriemann/consul2nginx
Author: Aljosha Friemann
Author-email: aljosha.friemann@gmail.com
License: UNKNOWN
Keywords: consul,proxy,nginx,configuration
Platform: linux
